dqtrader_rs.cp312-win_amd64.pyd
dqtrader/__init__.py
dqtrader/dqtrader.pyi
dqtrader/enums.py
dqtrader/__pycache__/__init__.cpython-311.pyc
dqtrader/__pycache__/enums.cpython-311.pyc
dqtrader/account/__init__.py
dqtrader/account/__pycache__/__init__.cpython-311.pyc
dqtrader/api/__init__.py
dqtrader/api/utils.py
dqtrader/api/__pycache__/__init__.cpython-311.pyc
dqtrader/api/__pycache__/utils.cpython-311.pyc
dqtrader/api/history/__init__.py
dqtrader/api/history/__pycache__/__init__.cpython-311.pyc
dqtrader/backtest/__init__.py
dqtrader/backtest/api.py
dqtrader/backtest/domain.py
dqtrader/backtest/order.py
dqtrader/backtest/order_var.py
dqtrader/backtest/__pycache__/__init__.cpython-311.pyc
dqtrader/backtest/__pycache__/api.cpython-311.pyc
dqtrader/backtest/__pycache__/domain.cpython-311.pyc
dqtrader/backtest/__pycache__/order.cpython-311.pyc
dqtrader/backtest/__pycache__/order_var.cpython-311.pyc
dqtrader/backtest_environment/__init__.py
dqtrader/backtest_environment/__pycache__/__init__.cpython-311.pyc
dqtrader/calcfactor/__init__.py
dqtrader/calcfactor/api.py
dqtrader/calcfactor/__pycache__/__init__.cpython-311.pyc
dqtrader/calcfactor/__pycache__/api.cpython-311.pyc
dqtrader/common/__init__.py
dqtrader/common/__pycache__/__init__.cpython-311.pyc
dqtrader/context/__init__.py
dqtrader/context/__pycache__/__init__.cpython-311.pyc
dqtrader/decorator/__init__.py
dqtrader/decorator/__pycache__/__init__.cpython-311.pyc
dqtrader/entity/__init__.py
dqtrader/entity/position_entity.py
dqtrader/entity/__pycache__/__init__.cpython-311.pyc
dqtrader/entity/__pycache__/position_entity.cpython-311.pyc
dqtrader/exception/__init__.py
dqtrader/exception/__pycache__/__init__.cpython-311.pyc
dqtrader/fmt/__init__.py
dqtrader/fmt/__pycache__/__init__.cpython-311.pyc
dqtrader/log/__init__.py
dqtrader/log/__pycache__/__init__.cpython-311.pyc
dqtrader/real_environment/__init__.py
dqtrader/real_environment/__pycache__/__init__.cpython-311.pyc
dqtrader/realtrade/__init__.py
dqtrader-0.0.31.dist-info/METADATA
dqtrader-0.0.31.dist-info/WHEEL
dqtrader-0.0.31.dist-info/top_level.txt
dqtrader-0.0.31.dist-info/RECORD
