Metadata-Version: 2.4
Name: dqtrader
Version: 0.0.31
Summary: DQT Python 工具箱
Dynamic: description
Dynamic: summary
